{
  "errors": [],
  "warnings": [],
  "version": "4.46.0",
  "hash": "3f5bbc74ec02abc49a4e",
  "publicPath": "/static/",
  "outputPath": "C:\\Users\\rodol\\OneDrive\\Documentos\\Projetos\\freelas\\FYDBR - Marina\\FYDBR\\build\\static",
  "assetsByChunkName": {
    "fydbr": [
      "fydbr.module.js",
      "fydbr.ff0f7a940b7ec5b78a86.hot-update.js"
    ],
    "list": "list.module.js"
  },
  "assets": [
    {
      "name": "ff0f7a940b7ec5b78a86.hot-update.json",
      "size": 47,
      "chunks": [],
      "chunkNames": [],
      "info": {
        "hotModuleReplacement": true,
        "immutable": true
      },
      "emitted": false
    },
    {
      "name": "fonts/DINPro-Cond.woff2",
      "size": 31088,
      "chunks": [],
      "chunkNames": [],
      "info": {},
      "emitted": false
    },
    {
      "name": "fonts/DINPro-CondBold.woff2",
      "size": 30700,
      "chunks": [],
      "chunkNames": [],
      "info": {},
      "emitted": false
    },
    {
      "name": "fonts/DINPro-CondMedium.woff2",
      "size": 31372,
      "chunks": [],
      "chunkNames": [],
      "info": {},
      "emitted": false
    },
    {
      "name": "fonts/DINPro-Light.woff2",
      "size": 33956,
      "chunks": [],
      "chunkNames": [],
      "info": {},
      "emitted": false
    },
    {
      "name": "fydbr.ff0f7a940b7ec5b78a86.hot-update.js",
      "size": 42740,
      "chunks": [
        "fydbr"
      ],
      "chunkNames": [
        "fydbr"
      ],
      "info": {
        "hotModuleReplacement": true,
        "immutable": true
      },
      "emitted": false
    },
    {
      "name": "fydbr.module.js",
      "size": 8338345,
      "chunks": [
        "fydbr"
      ],
      "chunkNames": [
        "fydbr"
      ],
      "info": {},
      "emitted": false
    },
    {
      "name": "images/Logo_final_morcego.svg",
      "size": 75752,
      "chunks": [],
      "chunkNames": [],
      "info": {},
      "emitted": false
    },
    {
      "name": "list.module.js",
      "size": 52824,
      "chunks": [
        "list"
      ],
      "chunkNames": [
        "list"
      ],
      "info": {},
      "emitted": false
    }
  ],
  "filteredAssets": 0,
  "entrypoints": {
    "fydbr": {
      "chunks": [
        "fydbr"
      ],
      "assets": [
        "fydbr.module.js",
        "fydbr.ff0f7a940b7ec5b78a86.hot-update.js"
      ],
      "children": {},
      "childAssets": {}
    }
  },
  "namedChunkGroups": {
    "fydbr": {
      "chunks": [
        "fydbr"
      ],
      "assets": [
        "fydbr.module.js",
        "fydbr.ff0f7a940b7ec5b78a86.hot-update.js"
      ],
      "children": {},
      "childAssets": {}
    },
    "list": {
      "chunks": [
        "list"
      ],
      "assets": [
        "list.module.js"
      ],
      "children": {},
      "childAssets": {}
    }
  },
  "logging": {
    "webpack.buildChunkGraph.visitModules": {
      "entries": [],
      "filteredEntries": 5,
      "debug": false
    }
  },
  "children": []
}